app/__init__.py
app/agents/__init__.py
app/agents/agent.py
app/agents/agent_converse.py
app/agents/prompts.py
app/main.py
app/prompts/default/architecture/01-explain-package-structure.md
app/prompts/default/architecture/02-explain-code-functionality.md
app/prompts/default/development/01-time-complexity.md
app/prompts/default/development/02-eliminate-duplication.md
app/prompts/default/development/03-error-handling.md
app/prompts/default/development/04-add-code-comments.md
app/prompts/default/documentation/01-generate-readme.md
app/prompts/default/review/01-evaluate-code-readability.md
app/prompts/default/review/02-evaluate-security-practices.md
app/prompts/default/review/03-check-unused-code.md
app/prompts/default/testing/01-generate-unit-tests.md
app/server.py
app/utils/__init__.py
app/utils/backup_diff_patch.py
app/utils/code_util.py
app/utils/directory_util.py
app/utils/file_util.py
app/utils/gitignore_parser.py
app/utils/langchain_validation_util.py
app/utils/logging_utils.py
app/utils/markdown_utils.py
app/utils/mertrics_utils.py
app/utils/print_tree_util.py
pyproject.toml
scripts.py
templates/asset-manifest.json
templates/favicon.ico
templates/index.html
templates/static/css/main.5f5a0496.css
templates/static/css/main.5f5a0496.css.map
templates/static/js/581.2bfe0b7f.chunk.js
templates/static/js/581.2bfe0b7f.chunk.js.map
templates/static/js/main.d0cd7b7e.js
templates/static/js/main.d0cd7b7e.js.LICENSE.txt
templates/static/js/main.d0cd7b7e.js.map
templates/static/media/codeforge_logo.b46c45655400df260980.png
templates/static/media/fa-brands-400.26b80c8830bebf340211.ttf
templates/static/media/fa-brands-400.fdbb558523a380307689.woff2
templates/static/media/fa-regular-400.05fdd87be89f7f8f0a1e.ttf
templates/static/media/fa-regular-400.4f6a2dabee9c092d09b9.woff2
templates/static/media/fa-solid-900.83a538a018a9e44b023a.woff2
templates/static/media/fa-solid-900.ad1782c70927ebc5bc87.ttf
templates/static/media/fa-v4compatibility.c3ea317a0f10f201597f.woff2
codeforge_ai-1.2.dist-info/METADATA
codeforge_ai-1.2.dist-info/WHEEL
codeforge_ai-1.2.dist-info/entry_points.txt
codeforge_ai-1.2.dist-info/RECORD
