Metadata-Version: 2.1
Name: codeforge-ai
Version: 1.2
Summary: 
Author: SWA-QA Team
Author-email: cct-qa@amazon.com
Requires-Python: >=3.9,<4.0
Classifier: Programming Language :: Python :: 3
Classifier: Programming Language :: Python :: 3.9
Classifier: Programming Language :: Python :: 3.10
Classifier: Programming Language :: Python :: 3.11
Classifier: Programming Language :: Python :: 3.12
Classifier: Programming Language :: Python :: 3.13
Requires-Dist: boto3 (>=1.34.88,<2.0.0)
Requires-Dist: httpx (==0.27.2)
Requires-Dist: jinja2 (>=3.1.3,<4.0.0)
Requires-Dist: langchain (>=0.3,<0.4)
Requires-Dist: langchain-anthropic (>=0.2,<0.3)
Requires-Dist: langchain-aws (>=0.2,<0.3)
Requires-Dist: langchain-cli (>=0.0.15)
Requires-Dist: langchain-community (>=0.3.1,<0.4.0)
Requires-Dist: langchainhub (>=0.1.15)
Requires-Dist: langgraph (>=0.2,<0.3)
Requires-Dist: pydantic (>=2.9.2,<3.0.0)
Requires-Dist: pydevd-pycharm (>=243.18137.19,<244.0.0)
Requires-Dist: python-multipart (==0.0.20)
Requires-Dist: pytz (==2024.2)
Requires-Dist: tiktoken (>=0.8.0,<0.9.0)
Requires-Dist: uvicorn (>=0.23.2,<0.24.0)
